Products.PloneHotfix20200121-1.1-py2.7-nspkg.pth
Products/PloneHotfix20200121/README.txt
Products/PloneHotfix20200121/__init__.py
Products/PloneHotfix20200121/content.py
Products/PloneHotfix20200121/in_portal.py
Products/PloneHotfix20200121/layout.py
Products/PloneHotfix20200121/pac.py
Products/PloneHotfix20200121/password_validation.py
Products/PloneHotfix20200121/restapi_local_roles.py
Products/PloneHotfix20200121/sql_quote.py
Products/PloneHotfix20200121/utils.py
Products/PloneHotfix20200121/tests/__init__.py
Products/PloneHotfix20200121/tests/test_102_in_portal.py
Products/PloneHotfix20200121/tests/test_122_124_in_portal.py
Products/PloneHotfix20200121/tests/test_129_password_validation.py
Products/PloneHotfix20200121/tests/test_130_pac.py
Products/PloneHotfix20200121/tests/test_134_sql_quote.py
Products/PloneHotfix20200121/tests/test_135_in_portal.py
Products/PloneHotfix20200121/tests/test_137_restapi_local_roles.py
Products/PloneHotfix20200121/tests/test_139_layout.py
Products.PloneHotfix20200121-1.1.dist-info/METADATA
Products.PloneHotfix20200121-1.1.dist-info/WHEEL
Products.PloneHotfix20200121-1.1.dist-info/entry_points.txt
Products.PloneHotfix20200121-1.1.dist-info/namespace_packages.txt
Products.PloneHotfix20200121-1.1.dist-info/top_level.txt
Products.PloneHotfix20200121-1.1.dist-info/RECORD
